{"_path":"/programming-languages/js/arrow-functions","_dir":"js","_draft":false,"_partial":false,"_locale":"","title":"Arrow Functions","description":"","body":{"type":"root","children":[{"type":"element","tag":"h2","props":{"id":"arrow-functions"},"children":[{"type":"text","value":"Arrow functions"}]},{"type":"element","tag":"ul","props":{},"children":[{"type":"element","tag":"li","props":{},"children":[{"type":"text","value":"syntactic sugar. removed need for\n"},{"type":"element","tag":"ul","props":{},"children":[{"type":"element","tag":"li","props":{},"children":[{"type":"text","value":"return keyword"}]},{"type":"element","tag":"li","props":{},"children":[{"type":"text","value":"function keyword"}]},{"type":"element","tag":"li","props":{},"children":[{"type":"text","value":"curly brackets"}]}]}]}]},{"type":"element","tag":"h3","props":{"id":"when-not-to-use-arrow-function"},"children":[{"type":"text","value":"When not to use arrow function"}]},{"type":"element","tag":"h4","props":{"id":"object-methods"},"children":[{"type":"text","value":"Object Methods"}]},{"type":"element","tag":"pre","props":{"className":["language-js"],"code":"const mario = {\n    lives: 3,\n    oneUp: () => {\n        this.lives++; // this will not update lives\n    }\n}\n","language":"js","meta":""},"children":[{"type":"element","tag":"code","props":{"__ignoreMap":""},"children":[{"type":"text","value":"const mario = {\n    lives: 3,\n    oneUp: () => {\n        this.lives++; // this will not update lives\n    }\n}\n"}]}]},{"type":"element","tag":"ul","props":{},"children":[{"type":"element","tag":"li","props":{},"children":[{"type":"text","value":"Arrow function do not have their own "},{"type":"element","tag":"code","props":{"className":[]},"children":[{"type":"text","value":"this"}]}]},{"type":"element","tag":"li","props":{},"children":[{"type":"text","value":"this.lives will refer to outer environment"}]}]},{"type":"element","tag":"h4","props":{"id":"object-prototype"},"children":[{"type":"text","value":"Object prototype"}]},{"type":"element","tag":"h4","props":{"id":"dynamic-context"},"children":[{"type":"text","value":"Dynamic context"}]},{"type":"element","tag":"ul","props":{},"children":[{"type":"element","tag":"li","props":{},"children":[{"type":"text","value":"arrow functions bind context statically. ie upon function declaration"}]}]},{"type":"element","tag":"p","props":{},"children":[{"type":"element","tag":"a","props":{"href":"https://medium.com/better-programming/3-examples-of-when-not-to-use-javascript-arrow-functions-90eebfbf7bb0","rel":["nofollow"]},"children":[{"type":"text","value":"When not to use arrow functions"}]},{"type":"element","tag":"a","props":{"href":"https://github.com/lydiahallie/javascript-questions#3-whats-the-output","rel":["nofollow"]},"children":[{"type":"text","value":"Question that provoked this thought"}]}]}],"toc":{"title":"","searchDepth":2,"depth":2,"links":[{"id":"arrow-functions","depth":2,"text":"Arrow functions","children":[{"id":"when-not-to-use-arrow-function","depth":3,"text":"When not to use arrow function"}]}]}},"_type":"markdown","_id":"content:programming-languages:js:arrow-functions.md","_source":"content","_file":"programming-languages/js/arrow-functions.md","_extension":"md"}