{"_path":"/programming-languages/js/instanceof","_dir":"js","_draft":false,"_partial":false,"_locale":"","title":"InstanceOf","description":"","body":{"type":"root","children":[{"type":"element","tag":"h3","props":{"id":"instanceof"},"children":[{"type":"text","value":"instanceof"}]},{"type":"element","tag":"ul","props":{},"children":[{"type":"element","tag":"li","props":{},"children":[{"type":"text","value":"complete keyword is in lower case"}]}]},{"type":"element","tag":"pre","props":{"className":["language-js"],"code":"let a = new Animal()\na instanceof Object //true\na instanceof Animal //true\na instanceof People //false\n","language":"js","meta":""},"children":[{"type":"element","tag":"code","props":{"__ignoreMap":""},"children":[{"type":"text","value":"let a = new Animal()\na instanceof Object //true\na instanceof Animal //true\na instanceof People //false\n"}]}]}],"toc":{"title":"","searchDepth":2,"depth":2,"links":[{"id":"instanceof","depth":3,"text":"instanceof"}]}},"_type":"markdown","_id":"content:programming-languages:js:instanceOf.md","_source":"content","_file":"programming-languages/js/instanceOf.md","_extension":"md"}